{
    " ": 6,
    "的": 3,
    "無": 2,
    "不是": 2,
    "有": 2,
    "推動": 2,
    "是": 2,
    "大事": 2,
    "兩用": 1,
    "水陸": 1,
    "車治": 1,
    "水患": 1,
    "之": 1,
    "類款": 1,
    "項": 1,
    "問題": 1,
    "方式": 1,
    "治水": 1,
    "房屋": 1,
    "水上": 1,
    "讀軍校": 1,
    "人": 1,
    "台灣": 1,
    "台南市": 1,
    "第二": 1,
    "事": 1,
    "選區": 1,
    "中華民國": 1,
    "國家": 1,
    "開始": 1,
    "小": 1,
    "工資": 1,
    "立法": 1,
    "委員": 1,
    "國中國": 1,
    "競標": 1,
    "錢莊": 1,
    "政府": 1,
    "廢除": 1,
    "滯納金": 1,
    "罰金": 1,
    "不合理": 1,
    "之金": 1,
    "競選金": 1,
    "貼": 1,
    "競選補": 1,
    "金": 1,
    "政治": 1,
    "獻金": 1,
    "交通": 1,
    "路邊": 1,
    "嚴格": 1,
    "信用卡": 1,
    "監督": 1,
    "廠商": 1,
    "工程": 1,
    "修法": 1,
    "國民": 1,
    "推出": 1,
    "關事項": 1,
    "停車": 1,
    "款稅": 1,
    "金之類": 1,
    "條款": 1,
    "沒給": 1
}