{"公辦政見會":[{"electiondefineno":"10402001","electiondefinename":"第14任總統副總統選舉","electiontypeno":"02","electiontypename":"總統副總統選舉","provinceno":"00","cityno":"000","cityname":"全國","electionarea":"0000000000","vno":"1","cvideoevent":"1","vtitle":"總統候選人政見發表會","vdateb":"Dec 25, 2015 8:00:00 PM","vtype":"電視","vplace":"民視","embed":"\u003ciframe width\u003d\"560\" height\u003d\"315\" src\u003d\"https://www.youtube.com/embed/KtH5E6HnXqI?rel\u003d0\" frameborder\u003d\"0\" allowfullscreen\u003e\u003c/iframe\u003e"},{"electiondefineno":"10402001","electiondefinename":"第14任總統副總統選舉","electiontypeno":"02","electiontypename":"總統副總統選舉","provinceno":"00","cityno":"000","cityname":"全國","electionarea":"0000000000","vno":"2","cvideoevent":"2","vtitle":"總統候選人政見發表會","vdateb":"Dec 30, 2015 8:00:00 PM","vtype":"電視","vplace":"華視","embed":"\u003ciframe width\u003d\"560\" height\u003d\"315\" src\u003d\"https://www.youtube.com/embed/ZQLLEFdBCkU?rel\u003d0\" frameborder\u003d\"0\" allowfullscreen\u003e\u003c/iframe\u003e"},{"electiondefineno":"10402001","electiondefinename":"第14任總統副總統選舉","electiontypeno":"02","electiontypename":"總統副總統選舉","provinceno":"00","cityno":"000","cityname":"全國","electionarea":"0000000000","vno":"3","cvideoevent":"3","vtitle":"總統候選人政見發表會","vdateb":"Jan 8, 2016 8:00:00 PM","vtype":"電視","vplace":"台視","embed":"\u003ciframe width\u003d\"560\" height\u003d\"315\" src\u003d\"https://www.youtube.com/embed/dq7haRJs9Zc?rel\u003d0\" frameborder\u003d\"0\" allowfullscreen\u003e\u003c/iframe\u003e"},{"electiondefineno":"10402001","electiondefinename":"第14任總統副總統選舉","electiontypeno":"02","electiontypename":"總統副總統選舉","provinceno":"00","cityno":"000","cityname":"全國","electionarea":"0000000000","vno":"4","cvideoevent":"1","vtitle":"副總統候選人政見發表會","vdateb":"Jan 4, 2016 8:00:00 PM","vtype":"電視","vplace":"公視","embed":"\u003ciframe width\u003d\"560\" height\u003d\"315\" src\u003d\"https://www.youtube.com/embed/m5bQw_txfZE?rel\u003d0\" frameborder\u003d\"0\" allowfullscreen\u003e\u003c/iframe\u003e"},{"electiondefineno":"10406001","electiondefinename":"第9屆平地原住民立法委員選舉","electiontypeno":"06","electiontypename":"立法委員選舉(平地原住民)","provinceno":"00","cityno":"000","cityname":"全國","electionarea":"0000000000","vno":"1","cvideoevent":"1","vtitle":"平地原住民立法委員候選人政見發表會","vdateb":"Jan 6, 2016 2:30:00 PM","vtype":"電視","vplace":"原民台","embed":"\u003ciframe width\u003d\"560\" height\u003d\"315\" src\u003d\"https://www.youtube.com/embed/M1s7Mt-IiC8?rel\u003d0\" frameborder\u003d\"0\" allowfullscreen\u003e\u003c/iframe\u003e"},{"electiondefineno":"10407001","electiondefinename":"第9屆山地原住民立法委員選舉","electiontypeno":"07","electiontypename":"立法委員選舉(山地原住民)","provinceno":"00","cityno":"000","cityname":"全國","electionarea":"0000000000","vno":"1","cvideoevent":"1","vtitle":"山地原住民立法委員候選人政見發表會","vdateb":"Jan 6, 2016 9:30:00 AM","vtype":"電視","vplace":"原民台","embed":"\u003ciframe width\u003d\"560\" height\u003d\"315\" src\u003d\"https://www.youtube.com/embed/8aGqUA3H-ps?rel\u003d0\" frameborder\u003d\"0\" allowfullscreen\u003e\u003c/iframe\u003e"}]}