{
    " ": 12,
    "更": 2,
    "廣建": 2,
    "正義": 2,
    "的": 2,
    "人格": 2,
    "教育": 2,
    "７": 1,
    "力推": 1,
    "支持": 1,
    "住宅": 1,
    "非核": 1,
    "家園強": 1,
    "政府": 1,
    "概念": 1,
    "以家": 1,
    "６": 1,
    "關廠": 1,
    "推動": 1,
    "房屋": 1,
    "動補助": 1,
    "督促": 1,
    "政策": 1,
    "社會": 1,
    "能板": 1,
    "保護動物": 1,
    "安全": 1,
    "托育": 1,
    "老人": 1,
    "10": 1,
    "迷你": 1,
    "水資源": 1,
    "蓄積": 1,
    "小水壩": 1,
    "關懷": 1,
    "生命": 1,
    "環保": 1,
    "８": 1,
    "勒令": 1,
    "第一": 1,
    "綠地": 1,
    "尊重": 1,
    "９": 1,
    "優先": 1,
    "太陽": 1,
    "捍衛食": 1,
    "取代": 1,
    "都": 1,
    "自主": 1,
    "建": 1,
    "商都": 1,
    "藍綠": 1,
    "超越": 1,
    "３": 1,
    "剝削": 1,
    "反": 1,
    "選舉": 1,
    "公費": 1,
    "宣揚": 1,
    "杜絕": 1,
    "財團": 1,
    "公平": 1,
    "２": 1,
    "干政": 1,
    "但求": 1,
    "４": 1,
    "扭曲": 1,
    "功利": 1,
    "令": 1,
    "學子": 1,
    "５": 1,
    "安源": 1,
    "安危": 1,
    "１": 1,
    "分致": 1,
    "100": 1,
    "養成": 1,
    "回歸": 1,
    "宣導": 1,
    "目標": 1,
    "而": 1,
    "追逐": 1,
    "不是": 1,
    "頭": 1
}